claude2_api/__init__.py
claude_api/__init__.py
claude_api/client.py
claude_api/errors.py
claude_api/session.py
unofficial_claude_api-0.3.3.dist-info/LICENSE
unofficial_claude_api-0.3.3.dist-info/METADATA
unofficial_claude_api-0.3.3.dist-info/WHEEL
unofficial_claude_api-0.3.3.dist-info/top_level.txt
unofficial_claude_api-0.3.3.dist-info/RECORD
