Metadata-Version: 2.1
Name: unofficial-claude-api
Version: 0.3.3
Summary: This unofficial Python API provides access to the conversational capabilities of Anthropic's Claude AI through a simple chat messaging interface.
Home-page: https://github.com/st1vms/unofficial-claude-api
Author: st1vms
Author-email: stefano.maria.salvatore@gmail.com
Classifier: Programming Language :: Python :: 3.10
Classifier: License :: OSI Approved :: MIT License
Classifier: Operating System :: OS Independent
Requires-Python: >=3.10
License-File: LICENSE
Requires-Dist: requests
Requires-Dist: selgym
Requires-Dist: curl-cffi
Requires-Dist: tzlocal
